winfcntl/__init__.py
winfcntl/setup.py
winfcntl/winfcntl.py
winfcntl-1.1.9.dist-info/METADATA
winfcntl-1.1.9.dist-info/WHEEL
winfcntl-1.1.9.dist-info/top_level.txt
winfcntl-1.1.9.dist-info/RECORD
