Metadata-Version: 2.1
Name: winfcntl
Version: 1.1.9
Summary: A fcntl solution for Windows Operating System
Author: Kiamehr Eskandari
Author-email: kiamehr13922014@gmail.com
Keywords: fcntl,windows,module,package,library
Classifier: Development Status :: 3 - Alpha
Classifier: Intended Audience :: Developers
Classifier: Programming Language :: Python :: 3
Classifier: Operating System :: Microsoft :: Windows
